pdfwidgets/__init__.py
pdfwidgets/utils.py
pdfwidgets-0.0.0.dist-info/METADATA
pdfwidgets-0.0.0.dist-info/WHEEL
pdfwidgets-0.0.0.dist-info/top_level.txt
pdfwidgets-0.0.0.dist-info/RECORD
